setup.py
notch/__init__.py
notch.agent.egg-info/PKG-INFO
notch.agent.egg-info/SOURCES.txt
notch.agent.egg-info/dependency_links.txt
notch.agent.egg-info/entry_points.txt
notch.agent.egg-info/namespace_packages.txt
notch.agent.egg-info/requires.txt
notch.agent.egg-info/top_level.txt
notch.agent.egg-info/zip-safe
notch/agent/__init__.py
notch/agent/__main__.py
notch/agent/agent.py
notch/agent/applications.py
notch/agent/controller.py
notch/agent/credential.py
notch/agent/device_factory.py
notch/agent/device_manager.py
notch/agent/errors.py
notch/agent/handlers.py
notch/agent/lru.py
notch/agent/notch_config.py
notch/agent/session.py
notch/agent/tp.py
notch/agent/utils.py
notch/agent/wsgi.py
notch/agent/devices/__init__.py
notch/agent/devices/dev_adva_fsp.py
notch/agent/devices/dev_arbor.py
notch/agent/devices/dev_binos.py
notch/agent/devices/dev_ftos.py
notch/agent/devices/dev_ios.py
notch/agent/devices/dev_junos.py
notch/agent/devices/dev_netscreen.py
notch/agent/devices/dev_nortel_bay.py
notch/agent/devices/dev_nortel_esr.py
notch/agent/devices/dev_nortel_esu.py
notch/agent/devices/dev_nos.py
notch/agent/devices/dev_omniswitch.py
notch/agent/devices/dev_paramiko.py
notch/agent/devices/dev_timos.py
notch/agent/devices/device.py
notch/agent/devices/paramiko_expect.py
notch/agent/devices/scp.py
notch/agent/devices/trans.py
notch/agent/devices/trans_paramiko_expect.py
notch/agent/devices/trans_ssh.py
notch/agent/devices/trans_telnet.py